python_web3_wallet/README
python_web3_wallet/__init__.py
python_web3_wallet/app.py
python_web3_wallet/frontend/.env.example
python_web3_wallet/frontend/.prettierrc
python_web3_wallet/frontend/build/asset-manifest.json
python_web3_wallet/frontend/build/bootstrap.min.css
python_web3_wallet/frontend/build/index.html
python_web3_wallet/frontend/build/static/css/main.81a73c2c.css
python_web3_wallet/frontend/build/static/js/1004.eeef2485.chunk.js
python_web3_wallet/frontend/build/static/js/1031.b71b6424.chunk.js
python_web3_wallet/frontend/build/static/js/1120.fe871836.chunk.js
python_web3_wallet/frontend/build/static/js/1168.a2d1fc04.chunk.js
python_web3_wallet/frontend/build/static/js/1207.7d274a1e.chunk.js
python_web3_wallet/frontend/build/static/js/1212.cc3caae9.chunk.js
python_web3_wallet/frontend/build/static/js/1841.dbcfd79c.chunk.js
python_web3_wallet/frontend/build/static/js/1845.20faeb33.chunk.js
python_web3_wallet/frontend/build/static/js/1876.c5e85a31.chunk.js
python_web3_wallet/frontend/build/static/js/1968.853d53af.chunk.js
python_web3_wallet/frontend/build/static/js/2012.5f5c0c61.chunk.js
python_web3_wallet/frontend/build/static/js/2024.0a3ddacc.chunk.js
python_web3_wallet/frontend/build/static/js/2240.9e4d6c6a.chunk.js
python_web3_wallet/frontend/build/static/js/2326.8f92f66f.chunk.js
python_web3_wallet/frontend/build/static/js/2645.fc70dec4.chunk.js
python_web3_wallet/frontend/build/static/js/2678.974f477e.chunk.js
python_web3_wallet/frontend/build/static/js/2692.6c784840.chunk.js
python_web3_wallet/frontend/build/static/js/2777.f3c79f9b.chunk.js
python_web3_wallet/frontend/build/static/js/2777.f3c79f9b.chunk.js.LICENSE.txt
python_web3_wallet/frontend/build/static/js/290.a75d4c37.chunk.js
python_web3_wallet/frontend/build/static/js/297.58e30fb4.chunk.js
python_web3_wallet/frontend/build/static/js/3019.633439b7.chunk.js
python_web3_wallet/frontend/build/static/js/3034.bea4ed94.chunk.js
python_web3_wallet/frontend/build/static/js/317.7246ebbb.chunk.js
python_web3_wallet-0.0.17.dist-info/METADATA
python_web3_wallet-0.0.17.dist-info/WHEEL
python_web3_wallet-0.0.17.dist-info/RECORD
