Metadata-Version: 2.3
Name: python-web3-wallet
Version: 0.0.17
Summary: Streamlit component that allows users to connect a wallet and send transactions with dynamic recipients and amounts
License: MIT
Author: Gnosis AI
Author-email: ai@gnosis.io
Requires-Python: >=3.10,<4.0
Classifier: License :: OSI Approved :: MIT License
Classifier: Programming Language :: Python :: 3
Classifier: Programming Language :: Python :: 3.10
Classifier: Programming Language :: Python :: 3.11
Classifier: Programming Language :: Python :: 3.12
Classifier: Programming Language :: Python :: 3.13
Requires-Dist: streamlit (>=1.49.0,<2.0.0)
